confprint/__init__.py
confprint/_exceptions.py
confprint/err_print.py
confprint/format.py
confprint/prefix_printer.py
confprint-0.5.1.dist-info/entry_points.txt
confprint-0.5.1.dist-info/LICENSE
confprint-0.5.1.dist-info/WHEEL
confprint-0.5.1.dist-info/METADATA
confprint-0.5.1.dist-info/RECORD
