Metadata-Version: 2.1
Name: confprint
Version: 0.5.1
Summary: Python printer configurations.
Home-page: https://github.com/lewiuberg/confprint
License: MIT
Keywords: print,printer configurations,prefix,stderr
Author: Lewi Lie Uberg
Author-email: lewi@uberg.me
Requires-Python: >=3.8,<4.0
Classifier: Development Status :: 1 - Planning
Classifier: Intended Audience :: Developers
Classifier: License :: OSI Approved :: MIT License
Classifier: Natural Language :: English
Classifier: Operating System :: MacOS
Classifier: Operating System :: Microsoft :: Windows
Classifier: Operating System :: POSIX :: Linux
Classifier: Programming Language :: Python :: 3
Classifier: Programming Language :: Python :: 3.10
Classifier: Programming Language :: Python :: 3.8
Classifier: Programming Language :: Python :: 3.9
Classifier: Topic :: Software Development :: Libraries :: Python Modules
Classifier: Topic :: Terminals
Classifier: Topic :: Utilities
Requires-Dist: click (==7.1.2)
Requires-Dist: colorama (>=0.4.4,<0.5.0)
Project-URL: Documentation, https://github.com/lewiuberg/confprint/README.md
Project-URL: Repository, https://github.com/lewiuberg/confprint
